nogenshin/__init__.py
nogenshin/decorators.py
nogenshin-0.2.0.dist-info/LICENSE
nogenshin-0.2.0.dist-info/METADATA
nogenshin-0.2.0.dist-info/WHEEL
nogenshin-0.2.0.dist-info/top_level.txt
nogenshin-0.2.0.dist-info/RECORD
