Metadata-Version: 2.1
Name: nogenshin
Version: 0.2.0
Summary: Genshin, but no Genshin.
Home-page: https://github.com/Charley-xiao/nogenshin
Author: Charley Xiao
Author-email: charleyxiao057@gmail.com
Classifier: Programming Language :: Python :: 3
Classifier: Operating System :: OS Independent
Requires-Python: >=3.6
License-File: LICENSE
